biblebot/__init__.py
biblebot/__main__.py
biblebot/auth.py
biblebot/bot.py
biblebot/cli.py
biblebot/log_utils.py
biblebot/setup_utils.py
biblebot/update_check.py
biblebot/constants/__init__.py
biblebot/constants/api.py
biblebot/constants/app.py
biblebot/constants/bible.py
biblebot/constants/config.py
biblebot/constants/logging.py
biblebot/constants/matrix.py
biblebot/constants/messages.py
biblebot/constants/system.py
biblebot/constants/update.py
biblebot/tools/__init__.py
biblebot/tools/biblebot.service
biblebot/tools/sample_config.yaml
matrix_biblebot-0.2.0.dist-info/licenses/LICENSE
matrix_biblebot-0.2.0.dist-info/METADATA
matrix_biblebot-0.2.0.dist-info/WHEEL
matrix_biblebot-0.2.0.dist-info/entry_points.txt
matrix_biblebot-0.2.0.dist-info/top_level.txt
matrix_biblebot-0.2.0.dist-info/RECORD
