Metadata-Version: 2.4
Name: matrix-biblebot
Version: 0.2.0
Summary: A simple Matrix bot that fetches Bible verses
Home-page: https://github.com/jeremiah-k/matrix-biblebot
Author: Jeremiah K
Author-email: jeremiahk@gmx.com
License: MIT
Project-URL: Bug Tracker, https://github.com/jeremiah-k/matrix-biblebot/issues
Classifier: Programming Language :: Python :: 3
Classifier: License :: OSI Approved :: MIT License
Classifier: Operating System :: OS Independent
Classifier: Development Status :: 4 - Beta
Classifier: Topic :: Communications
Requires-Python: >=3.9
License-File: LICENSE
Requires-Dist: matrix-nio<0.26,>=0.25.2
Requires-Dist: PyYAML~=6.0
Requires-Dist: python-dotenv~=1.1.0
Requires-Dist: aiohttp>=3.11.0
Requires-Dist: rich~=13.7
Requires-Dist: packaging~=24.0
Provides-Extra: test
Requires-Dist: pytest>=8.0.0; extra == "test"
Requires-Dist: pytest-asyncio>=0.21.0; extra == "test"
Requires-Dist: pytest-cov>=4.0; extra == "test"
Requires-Dist: pytest-aiohttp>=1.0; extra == "test"
Requires-Dist: coverage>=7.6; extra == "test"
Provides-Extra: e2e
Requires-Dist: matrix-nio[e2e]<0.26,>=0.25.2; extra == "e2e"
Dynamic: author
Dynamic: author-email
Dynamic: classifier
Dynamic: description
Dynamic: description-content-type
Dynamic: home-page
Dynamic: license
Dynamic: license-file
Dynamic: project-url
Dynamic: provides-extra
Dynamic: requires-dist
Dynamic: requires-python
Dynamic: summary
